stock_trader/__init__.py
stock_trader/__main__.py
stock_trader/py.typed
stock_trader-0.0.4.dist-info/entry_points.txt
stock_trader-0.0.4.dist-info/LICENSE.rst
stock_trader-0.0.4.dist-info/WHEEL
stock_trader-0.0.4.dist-info/METADATA
stock_trader-0.0.4.dist-info/RECORD
