Metadata-Version: 2.1
Name: stock-trader
Version: 0.0.4
Summary: Stock Trader
Home-page: https://github.com/ciresnave/stock_trader
License: MIT
Author: Eric Evans
Author-email: ciresnave@gmail.com
Requires-Python: >=3.6.1,<4.0.0
Classifier: License :: OSI Approved :: MIT License
Classifier: Programming Language :: Python :: 3
Classifier: Programming Language :: Python :: 3.6
Classifier: Programming Language :: Python :: 3.7
Classifier: Programming Language :: Python :: 3.8
Classifier: Programming Language :: Python :: 3.9
Provides-Extra: all
Provides-Extra: colorama
Provides-Extra: shellingham
Requires-Dist: colorama (>=0.4.4,<0.5.0); extra == "colorama" or extra == "all"
Requires-Dist: shellingham (>=1.4.0,<2.0.0); extra == "shellingham" or extra == "all"
Requires-Dist: typer (>=0.3.2,<0.4.0)
Project-URL: Changelog, https://github.com/ciresnave/stock_trader/releases
Project-URL: Documentation, https://stock_trader.readthedocs.io
Project-URL: Repository, https://github.com/ciresnave/stock_trader
